{
  "config": {
    "step": {
      "user": {
        "title": "Salus iT600 Cloud",
        "description": "Enter your Salus Cloud credentials",
        "data": {
          "email": "Email",
          "password": "Password"
        }
      }
    },
    "error": {
      "invalid_auth": "Invalid email or password",
      "no_devices": "No devices found on your account",
      "unknown": "Unexpected error occurred"
    },
    "abort": {
      "already_configured": "Account is already configured"
    }
  }
}
